devops_cli/__init__.py
devops_cli/aws.py
devops_cli/clinic.py
devops_cli/k8s.py
devops_cli/main.py
devops_cli/minio.py
devops_cli/rabbitmq.py
devops_cli/utils.py
devops_cli-0.3.0.dist-info/entry_points.txt
devops_cli-0.3.0.dist-info/LICENSE
devops_cli-0.3.0.dist-info/WHEEL
devops_cli-0.3.0.dist-info/METADATA
devops_cli-0.3.0.dist-info/RECORD
