Metadata-Version: 2.1
Name: devops-cli
Version: 0.3.0
Summary: A CLI tool that provides useful functions to operate on the Vital Beats cluster.
License: GPL-3.0
Author: Stephen Badger
Author-email: stephen.badger@vitalbeats.com
Requires-Python: >=3.7,<4
Classifier: License :: OSI Approved :: GNU General Public License v3 (GPLv3)
Classifier: Programming Language :: Python :: 3
Classifier: Programming Language :: Python :: 3.7
Classifier: Programming Language :: Python :: 3.8
Requires-Dist: boto3 (>=1.17.19,<2.0.0)
Requires-Dist: kubernetes (>=12.0.1,<13.0.0)
Requires-Dist: minio (>=7.0.3,<8.0.0)
Requires-Dist: pika (>=1.2.0,<2.0.0)
Requires-Dist: psycopg2-binary (>=2.8.6,<3.0.0)
